ciftools/__init__.py
ciftools/serialization.py
ciftools/binary/__init__.py
ciftools/binary/data.py
ciftools/binary/data_types.py
ciftools/binary/decoder.py
ciftools/binary/encoded_data.py
ciftools/binary/encoder.py
ciftools/binary/encoding_types.py
ciftools/binary/writer.py
ciftools/models/__init__.py
ciftools/models/data.py
ciftools/models/writer.py
ciftools-0.2.1.dist-info/licenses/LICENSE
ciftools-0.2.1.dist-info/METADATA
ciftools-0.2.1.dist-info/WHEEL
ciftools-0.2.1.dist-info/top_level.txt
ciftools-0.2.1.dist-info/RECORD
